README.rst
setup.py
dumbyaml/__init__.py
dumbyaml/dumbloader.py
dumbyaml/exceptions.py
dumbyaml/yamlnode.py
dumbyaml.egg-info/PKG-INFO
dumbyaml.egg-info/SOURCES.txt
dumbyaml.egg-info/dependency_links.txt
dumbyaml.egg-info/not-zip-safe
dumbyaml.egg-info/requires.txt
dumbyaml.egg-info/top_level.txt
dumbyaml/unittests/__init__.py
dumbyaml/unittests/test_dumbyaml.py